belt/__init__.py
belt/__main__.py
belt/cli.py
belt/loader.py
belt/models.py
belt/output_writer.py
belt/parser.py
belt/viability.py
brine_and_ember_belt-0.1.0.dist-info/METADATA
brine_and_ember_belt-0.1.0.dist-info/WHEEL
brine_and_ember_belt-0.1.0.dist-info/entry_points.txt
brine_and_ember_belt-0.1.0.dist-info/RECORD
