Metadata-Version: 2.4
Name: brine_and_ember-belt
Version: 0.1.0
Summary: Brine & Ember Life cycle analysis and Techno-economic analysis Tool for LCA/TEA scenario analysis
Project-URL: Homepage, https://github.com/yourusername/belt
Project-URL: Repository, https://github.com/yourusername/belt
Project-URL: Documentation, https://github.com/yourusername/belt#readme
Author-email: Joshua Book <joshua.book@gmail.com>
License: MIT
Keywords: biomass,carbon,lca,lifecycle-analysis,tea,techno-economic
Classifier: Development Status :: 3 - Alpha
Classifier: Environment :: Console
Classifier: Intended Audience :: Science/Research
Classifier: License :: OSI Approved :: MIT License
Classifier: Operating System :: OS Independent
Classifier: Programming Language :: Python :: 3
Classifier: Programming Language :: Python :: 3.12
Classifier: Topic :: Scientific/Engineering
Requires-Python: >=3.12
Requires-Dist: pydantic>=2.12.5
Requires-Dist: pyyaml>=6.0.3
Requires-Dist: typer>=0.21.1
Provides-Extra: dev
Requires-Dist: pytest>=9.0.2; extra == 'dev'
Requires-Dist: ruff>=0.4.0; extra == 'dev'
